<?xml version='1.0' encoding='UTF-8'?><org.mule.tooling.metadata.cache.MetadataCache><version>3.5.0.05</version><projectMetadataCache><entry><string>JSON_To_JSON_1JSON_To_JSON_2JSON_To_JSON_3</string><map><entry><string>http://www.mulesoft.org/schema/mule/ee/data-mapper/transform</string><map><entry><string>__default__</string><org.mule.tooling.metadata.cache.MetadataCache_-DefaultMetadataCacheEntry/></entry></map></entry></map></entry><entry><string>JSON_To_JSON_1</string><map><entry><string>http://www.mulesoft.org/schema/mule/ee/data-mapper/transform</string><map><entry><string>__default__</string><org.mule.tooling.metadata.cache.MetadataCache_-DefaultMetadataCacheEntry/></entry></map></entry></map></entry><entry><string>Extract_access_token</string><map><entry><string>http://www.mulesoft.org/schema/mule/ee/data-mapper/transform</string><map><entry><string>__default__</string><org.mule.tooling.metadata.cache.MetadataCache_-DefaultMetadataCacheEntry><output class="org.mule.common.metadata.DefaultMetaData"><payload class="org.mule.common.metadata.DefaultSimpleMetaDataModel"><dataType>STRING</dataType><metaDataModelPropertiesManager><properties/></metaDataModelPropertiesManager></payload><properties><entry><org.mule.common.metadata.MetaDataPropertyScope>INBOUND</org.mule.common.metadata.MetaDataPropertyScope><org.mule.common.metadata.MetaDataProperties><fields/></org.mule.common.metadata.MetaDataProperties></entry><entry><org.mule.common.metadata.MetaDataPropertyScope>OUTBOUND</org.mule.common.metadata.MetaDataPropertyScope><org.mule.common.metadata.MetaDataProperties><fields/></org.mule.common.metadata.MetaDataProperties></entry><entry><org.mule.common.metadata.MetaDataPropertyScope>SESSION</org.mule.common.metadata.MetaDataPropertyScope><org.mule.common.metadata.MetaDataProperties><fields/></org.mule.common.metadata.MetaDataProperties></entry><entry><org.mule.common.metadata.MetaDataPropertyScope>RECORD</org.mule.common.metadata.MetaDataPropertyScope><org.mule.common.metadata.MetaDataProperties><fields/></org.mule.common.metadata.MetaDataProperties></entry><entry><org.mule.common.metadata.MetaDataPropertyScope>FLOW</org.mule.common.metadata.MetaDataPropertyScope><org.mule.common.metadata.MetaDataProperties><fields/></org.mule.common.metadata.MetaDataProperties></entry></properties></output></org.mule.tooling.metadata.cache.MetadataCache_-DefaultMetadataCacheEntry></entry></map></entry></map></entry><entry><string>JSON_To_JSON_1JSON_To_JSON_2</string><map><entry><string>http://www.mulesoft.org/schema/mule/ee/data-mapper/transform</string><map><entry><string>__default__</string><org.mule.tooling.metadata.cache.MetadataCache_-DefaultMetadataCacheEntry/></entry></map></entry></map></entry><entry><string>JSON_To_JSON</string><map><entry><string>http://www.mulesoft.org/schema/mule/ee/data-mapper/transform</string><map><entry><string>__default__</string><org.mule.tooling.metadata.cache.MetadataCache_-DefaultMetadataCacheEntry/></entry></map></entry></map></entry><entry><string>JSON_To_JSON_1JSON_To_JSON_2JSON_To_JSON_3JSON_To_JSON_4</string><map><entry><string>http://www.mulesoft.org/schema/mule/ee/data-mapper/transform</string><map><entry><string>__default__</string><org.mule.tooling.metadata.cache.MetadataCache_-DefaultMetadataCacheEntry/></entry></map></entry></map></entry></projectMetadataCache></org.mule.tooling.metadata.cache.MetadataCache>